fustor_web_ui/__init__.py
fustor_web_ui/ui/app.js
fustor_web_ui/ui/index.html
fustor_web_ui/ui/style.css
fustor_web_ui/ui/css/components/ConfigListItem.css
fustor_web_ui/ui/css/components/LogPreview.css
fustor_web_ui/ui/css/views/DashboardView.css
fustor_web_ui/ui/css/views/LogsView.css
fustor_web_ui/ui/css/views/SyncTasksPageView.css
fustor_web_ui/ui/css/views/WizardView.css
fustor_web_ui/ui/js/apiService.js
fustor_web_ui/ui/js/navigation.js
fustor_web_ui/ui/js/notification.js
fustor_web_ui/ui/js/state.js
fustor_web_ui/ui/js/stateStore.js
fustor_web_ui/ui/js/utils.js
fustor_web_ui/ui/js/components/ConfigListItem.js
fustor_web_ui/ui/js/components/LogPreview.js
fustor_web_ui/ui/js/views/DashboardView.js
fustor_web_ui/ui/js/views/LogsView.js
fustor_web_ui/ui/js/views/ReceiversView.js
fustor_web_ui/ui/js/views/SourcesView.js
fustor_web_ui/ui/js/views/SyncTasksPageView.js
fustor_web_ui/ui/js/views/SyncWizardView.js
fustor_web_ui/ui/js/views/WizardView.js
fustor_web_ui/ui/js/views/wizard/WizardState.js
fustor_web_ui/ui/js/views/wizard/WizardUiComponents.js
fustor_web_ui-0.2.16.dist-info/METADATA
fustor_web_ui-0.2.16.dist-info/WHEEL
fustor_web_ui-0.2.16.dist-info/top_level.txt
fustor_web_ui-0.2.16.dist-info/RECORD
