Metadata-Version: 2.4
Name: fustor-web-ui
Version: 0.2.16
Summary: Web UI for Fustor Agent
Author-email: Huajin Wang <wanghuajin999@163.com>
Requires-Python: >=3.11
Requires-Dist: fustor-core
